{
  "mem_1758289015_0": {
    "id": "mem_1758289015_0",
    "content": "说: {\"online\":true,\"terminal\":0,\"userId\":46014}",
    "category": "用户状态信息",
    "importance": 4,
    "keywords": [],
    "created_at": 1758289015.4135098,
    "last_accessed": 1758289015.4135103,
    "access_count": 0,
    "related_users": [
      ""
    ],
    "related_messages": [],
    "emotional_context": "感觉有点好奇和兴奋",
    "memory_type": "factual",
    "confidence": 1.0,
    "source": "chat",
    "tags": []
  },
  "mem_1758289027_1": {
    "id": "mem_1758289027_1",
    "content": "{\"online\":false,\"terminal\":0,\"userId\":28638}",
    "category": "用户状态信息",
    "importance": 10,
    "keywords": [],
    "created_at": 1758289027.0791268,
    "last_accessed": 1758289264.343121,
    "access_count": 6,
    "related_users": [
      ""
    ],
    "related_messages": [],
    "emotional_context": "感觉有点好奇和兴奋",
    "memory_type": "factual",
    "confidence": 1.0,
    "source": "chat",
    "tags": []
  },
  "mem_1758289043_2": {
    "id": "mem_1758289043_2",
    "content": "{\"online\":true,\"terminal\":0,\"userId\":50989}",
    "category": "用户状态信息",
    "importance": 4,
    "keywords": [],
    "created_at": 1758289043.5639806,
    "last_accessed": 1758289043.5639808,
    "access_count": 0,
    "related_users": [
      ""
    ],
    "related_messages": [],
    "emotional_context": "感觉有点好奇和兴奋",
    "memory_type": "factual",
    "confidence": 1.0,
    "source": "chat",
    "tags": []
  },
  "mem_1758289060_3": {
    "id": "mem_1758289060_3",
    "content": "{\"online\":false,\"terminal\":0,\"userId\":58313}",
    "category": "用户状态信息",
    "importance": 7,
    "keywords": [],
    "created_at": 1758289060.295468,
    "last_accessed": 1758289205.7509892,
    "access_count": 3,
    "related_users": [
      ""
    ],
    "related_messages": [],
    "emotional_context": "感觉有点好奇和兴奋，想知道这些用户的状态变化",
    "memory_type": "factual",
    "confidence": 1.0,
    "source": "chat",
    "tags": []
  },
  "mem_1758289076_4": {
    "id": "mem_1758289076_4",
    "content": "{\"online\":true,\"terminal\":1,\"userId\":48110}",
    "category": "用户状态信息",
    "importance": 4,
    "keywords": [],
    "created_at": 1758289076.9111166,
    "last_accessed": 1758289076.9111168,
    "access_count": 0,
    "related_users": [
      ""
    ],
    "related_messages": [],
    "emotional_context": "感觉有点好奇和兴奋，想知道这些用户的状态变化",
    "memory_type": "factual",
    "confidence": 1.0,
    "source": "chat",
    "tags": []
  },
  "mem_1758289160_5": {
    "id": "mem_1758289160_5",
    "content": "说: {\"dissolve\":false,\"headImage\":\"https://www.boxim.online/file/box-im/image/20250901/1756739464960.png\",\"headImageThumb\":\"https://www.boxim.online/file/box-im/image/20250901/1756739464960.png\",\"id\":8212,\"isAllMuted\":false,\"isAllowInvite\":true,\"isAllowShareCard\":false,\"isBanned\":false,\"isMuted\":false,\"isTop\":false,\"name\":\"florr.io\",\"notice\":\"这是一个交流游戏florr.io的地方n群规1.16：n1.本群禁止大量刷屏，骂人，脏话等行为。也别在这里大量发电.一经发现，一律禁言。多次将会踢出群聊。n2.可以拉人，但对方必须是florr玩家n3.禁止把群名片发出去n4.管理员不可滥用职权，一经发现取消管理员身份n5.别涉黄，发现两次以上踢出，若认错诚恳可以加回n6.:)n本群规会不定时更新nn被禁言人员名单：Craft_Supern\",\"ownerId\":28923,\"quit\":false,\"reason\":\"\",\"remarkGroupName\":\"\",\"remarkNickName\":\"\",\"showGroupName\":\"florr.io\",\"showNickName\":\"Nbot\"}",
    "category": "群组信息",
    "importance": 4,
    "keywords": [],
    "created_at": 1758289160.0818436,
    "last_accessed": 1758289160.0818439,
    "access_count": 0,
    "related_users": [
      ""
    ],
    "related_messages": [],
    "emotional_context": "感觉有点好奇和兴奋，想知道这些用户的状态变化",
    "memory_type": "factual",
    "confidence": 1.0,
    "source": "chat",
    "tags": []
  },
  "mem_1758289174_6": {
    "id": "mem_1758289174_6",
    "content": "fkufff邀请Nbot加入了群聊",
    "category": "群组信息",
    "importance": 4,
    "keywords": [],
    "created_at": 1758289174.5525498,
    "last_accessed": 1758289174.55255,
    "access_count": 0,
    "related_users": [
      "fkufff"
    ],
    "related_messages": [],
    "emotional_context": "感觉有点好奇和兴奋，想知道这些用户的状态变化",
    "memory_type": "episodic",
    "confidence": 1.0,
    "source": "chat",
    "tags": []
  }
}